wconfig/__init__.py
wconfig-0.1.3.dist-info/METADATA
wconfig-0.1.3.dist-info/WHEEL
wconfig-0.1.3.dist-info/entry_points.txt
wconfig-0.1.3.dist-info/RECORD
