Metadata-Version: 2.4
Name: wconfig
Version: 0.1.3
Summary: 58WConfig配置平台工具
Author-email: 王梦迪 <wangmengdi06@58.com>
Requires-Python: >=3.10
Requires-Dist: docarray>=0.41.0
Requires-Dist: pydantic
Requires-Dist: requests>=2.32.4
